setup.py
classtoolz/__init__.py
classtoolz/cached.py
classtoolz/core.py
classtoolz/example.py
classtoolz/immutable.py
classtoolz/slotted.py
classtoolz/typed.py
classtoolz.egg-info/PKG-INFO
classtoolz.egg-info/SOURCES.txt
classtoolz.egg-info/dependency_links.txt
classtoolz.egg-info/not-zip-safe
classtoolz.egg-info/top_level.txt