Metadata-Version: 1.0
Name: classtoolz
Version: 0.1
Summary: Class utilities
Home-page: http://github.com/mrocklin/classtoolz
Author: Matthew Rocklin
Author-email: mrocklin@gmail.com
License: BSD
Platform: UNKNOWN
